akudu/__init__.py
akudu/client.py
akudu/connection.py
akudu/negotiate.py
akudu/wire.py
akudu-0.0.1.dist-info/LICENSE
akudu-0.0.1.dist-info/METADATA
akudu-0.0.1.dist-info/WHEEL
akudu-0.0.1.dist-info/top_level.txt
akudu-0.0.1.dist-info/RECORD
