Metadata-Version: 2.1
Name: akudu
Version: 0.0.1
Summary: Asyncio Client for Apache Kudu Database Engine (Storage System).
Home-page: http://github.com/lovinjoy/akudu
Author: LovinJoy
Author-email: technical-committee@lovinjoy.com
License: MIT License
Keywords: kudu,database,asyncio,bigdata,storage system
Requires-Python: >=3.8
License-File: LICENSE
Requires-Dist: protobuf (>=3.20.0)
